drf_inspect/__init__.py
drf_inspect/apps.py
drf_inspect/build.py
drf_inspect/helpers.py
drf_inspect/models.py
drf_inspect/use_cases/__init__.py
drf_inspect/use_cases/prefetch.py
drf_inspect-0.1.2b0.dist-info/METADATA
drf_inspect-0.1.2b0.dist-info/WHEEL
drf_inspect-0.1.2b0.dist-info/RECORD
