Metadata-Version: 2.4
Name: drf-inspect
Version: 0.1.2b0
Summary: django rest framework inspection helpers
Author-email: Andrei Samofalov <andrei.e.samofalov@gmail.com>
License-Expression: MIT
Classifier: Development Status :: 4 - Beta
Classifier: Programming Language :: Python
Classifier: Programming Language :: Python :: 3.11
Classifier: Programming Language :: Python :: 3.12
Classifier: Programming Language :: Python :: Implementation :: CPython
Classifier: Programming Language :: Python :: Implementation :: PyPy
Requires-Python: >=3.11
Requires-Dist: django==4.2.16
Requires-Dist: djangorestframework==3.15.2
Requires-Dist: pydantic>=2.11.7
